python_rhnapi-5.4.1.post3.dist-info/DESCRIPTION.rst
python_rhnapi-5.4.1.post3.dist-info/METADATA
python_rhnapi-5.4.1.post3.dist-info/RECORD
python_rhnapi-5.4.1.post3.dist-info/WHEEL
python_rhnapi-5.4.1.post3.dist-info/metadata.json
python_rhnapi-5.4.1.post3.dist-info/top_level.txt
rhnapi/__init__.py
rhnapi/activationkey.py
rhnapi/api.py
rhnapi/channel.py
rhnapi/configchannel.py
rhnapi/decorators.py
rhnapi/distchannel.py
rhnapi/errata.py
rhnapi/kickstart.py
rhnapi/org.py
rhnapi/packages.py
rhnapi/preferences.py
rhnapi/proxy.py
rhnapi/satellite.py
rhnapi/schedule.py
rhnapi/system.py
rhnapi/systemgroup.py
rhnapi/user.py
rhnapi/utils.py
