Metadata-Version: 2.0
Name: python-rhnapi
Version: 5.4.1.post3
Summary: Python abstraction of the RHN Satellite XMLRPC API
Home-page: https://github.com/pieterdp/python-rhnapi
Author: Stuart Sears
Author-email: sjs@redhat.com
License: GPL v2+
Platform: UNKNOWN
